FSM.v
	
`timescale 1ns / 1ps
`define IDLE 0
`define CALC 1
`define DONE 2

// FSM, maquina de estados finita

module FSM
(

// Señales de la FSM

	input wire Clock,
	input wire Reset,
	input wire valid_data,
	input wire ack,
// Señales del datapath
	input wire b_lsb,
	output reg a_sel,
	output reg b_sel,
	output reg prod_sel,
	output reg add_sel,
// Salida de para el test bench	
	output reg Done_Flag

);

	// contador de 6 bits para contar hasta 32.

	integer cont; 
	
	// Registros de estado actual y proximo estado.

	reg [1:0] CurrentState, NextState;

	reg a,b,c;

	// Registro proxima salida

	// reg NextOut; //Solo para hacer la salida sincrónica
	

	//Logica de Estado Presente y de Salida Sincrónica
	
	always @ ( posedge Clock, posedge Reset )

	begin
	
	// Si ocurre reset, coloque la maquina en el estado IDLE.

		if (Reset)

			begin
		
			CurrentState <= `IDLE;
		//	out <= 0;	
		
			end
			
		else

			begin
		
			CurrentState <= NextState;
		//	out <= NextOut;	
		
			end
			
	end
	
	
	//Lógica de Próximo Estado de Máquina Moore (Salida solo depende del estado)
	
	always @ ( posedge Clock )

	begin

		case (CurrentState)
			

			`IDLE:
			begin
				
			//	NextOut = 0; // LO TRAE POR DEFECTO EL CODIGO REVISAR!
				
				// Si valid_data es 0 mantengase en el estado IDLE.

				
				// En el estado IDLE la señal prod_sel selecciona
				// el producto inicializado en 0.

				prod_sel = 0;

				// En el estado IDLE la señal a_sel selecciona
				// el operando "a" inicial sin rotar.

				a_sel = 0;

				// En el estado IDLE la señal a_sel selecciona
				// el operando "b" inicial sin rotar.

				b_sel = 0;
				a = 0;
				b= 0;
				c=0;

				// Inicializacion de contador.

				cont = 0;


				// Se selecciona reg_prod mientras NO se cumpla b & 0x1 == 1:
				add_sel = 0;

				// Inicializacion de bandera done.
				Done_Flag = 0 ;


				if (valid_data == 0)

					NextState = `IDLE;
				
				// Si valid_data es 1 vaya al estado CALC.

				else

					NextState = `CALC;
				
				
			end
			

			`CALC:
			
			begin

				// lo traia por defecto el codigo, REVISAR.
			//	 NextOut = 1;


				// Cuando se ingresa al estado calcular el producto cambia respecto
				// a su valor inicial.

				prod_sel = 1;


				// En el estado CALC la señal a_sel selecciona
				// el operando "a" que ya  ha sido rotado.

				a_sel = 1;

				// En el estado CALC la señal a_sel selecciona
				// el operando "b" que ya ha sido rotado.

				b_sel = 1;


		
				
				// NextState = `CALC;
				if (cont < 32 && b_lsb == 1)
					
					begin

					a<=1;

					NextState = `CALC;

					// Si el bit lsb de b era 1 sumo al producto a.
					add_sel = 1;

					cont = cont + 1;

					end

				
				else if (cont <32 && b_lsb == 0)
					
					begin

					b=1;
							
					NextState = `CALC;

					cont = cont + 1;


					// Se selecciona reg_prod mientras NO se cumpla b & 0x1 == 1:
					add_sel = 1;

					end
				
				else 
					begin

					c= 1;
	
					NextState = `DONE;

					// Se selecciona reg_prod mientras NO se cumpla b & 0x1 == 1:
					add_sel = 0;

					// Reinicio del contador.

					cont = 0;

					end

	
			end
			
			`DONE:

			// El estado DONE envia el mensaje hacia afuera del multiplicador, 
			// el resultado se mantiene hasta que se reciba la señal ack que indica que el resultado fue leído.
			
			begin

			//	NextOut = 0;

			// Se selecciona reg_prod mientras NO se cumpla b & 0x1 == 1:
			add_sel = 0;

				// Si ack es 0 mantengase en el estado DONE.
				
				if (ack == 0)
					begin
					
					// Bandera que indica que el resultado esta listo.

					Done_Flag = 1;

					NextState = `DONE;

					end

				
				// Si ack es 1 vaya al estado IDLE.
				else
					
					begin

					// Bandera que indica que el resultado esta listo.
					
					Done_Flag = 0;

					NextState = `IDLE;

					end
			end
			
			default:
			
			begin

				NextState = `IDLE;
			//	NextOut = 0;

			end
		

		endcase

	end

endmodule

datapath.v
`timescale 1ns/1ps
`include "primitivas.v"

`define SIZE_DATA 32

module datapath(a,b,prod,b_sel,a_sel,prod_sel,b_lsb,add_sel,clk,reset);

	parameter size = `SIZE_DATA;
	// Inputs
	input [size-1:0] a,b;
	wire [size-1:0] a,b;
	input wire b_sel,a_sel,prod_sel,add_sel;
	input wire clk,reset;

	// Outputs
	output wire [2*size-1:0] prod;
	output wire b_lsb;
	
	// Mux A
	wire [size-1:0] outMuxA;
	wire [size-1:0] aShift;
	mux2NaN #(.size(32)) muxA (.select(a_sel),.d1(a),.d2(aShift),.q(outMuxA));
	
	// Mux B
	wire [size-1:0] outMuxB;
	wire [size-1:0] bShift;
	mux2NaN #(.size(32)) muxB (.select(b_sel),.d1(b),.d2(bShift),.q(outMuxB));
	
	// Mux prod
	wire [2*size-1:0] outMuxProd;
	wire [2*size-1:0] outAddSelMux;
	mux2NaN #(.size(64)) muxProd (.select(prod_sel),.d1(64'b0),.d2(outAddSelMux),.q(outMuxProd));
	
	// Reg A
	wire [size-1:0] outRegA;
	wire [size-1:0] outRegA_bar;
	regN #(.size(32)) regA (.in(outMuxA),.clk(clk),.clr(reset),.out(outRegA),.out_bar(outRegA_bar));
	
	// Reg B
	wire [size-1:0] outRegB;
	wire [size-1:0] outRegB_bar;
	regN #(.size(32)) regB (.in(outMuxB),.clk(clk),.clr(reset),.out(outRegB),.out_bar(outRegB_bar));
	// Se asigna el valor de b_lsb como el bit menos significativo de la salida del registro B.
	assign b_lsb = outRegB[0];
	
	// Reg Prod
	wire [2*size-1:0] outRegProd;
	wire [2*size-1:0] outRegProd_bar;
	regN #(.size(64)) regProd (.in(outMuxProd),.clk(clk),.clr(reset),.out(outRegProd),.out_bar(outRegProd_bar));
	
	// Shift A
	assign aShift = outRegA << 1;
	
	// Shift B
	assign bShift = outRegB >> 1;
	
	// Add A+Prod
	wire [2*size-1:0] addResult;
	adderN #(.size(64)) sumador64 ({32'b0,outRegA},outRegProd,addResult);
	
	
	// Mux add_sel
	mux2NaN #(.size(64)) muxAddSel(.select(add_sel),.d1(outRegProd),.d2(addResult),.q(outAddSelMux));
	
	assign prod = outRegProd;
	
	
endmodule

multiplicador.v
`timescale 1ns/1ps
`include "datapath.v"
`include "FSM.v"

module multiplicador(prod, Done_Flag, a, b, clk, reset, valid_data, ack);

	output [63:0] prod;
	output Done_Flag;
	input [31:0] a, b;
	input clk,reset,valid_data,ack;

	datapath data(a, b, prod, b_sel, a_sel, prod_sel, b_lsb, add_sel, clk, reset);

	FSM control(
		.Clock(clk),
		.Reset(reset),
		.valid_data(valid_data),
		.ack(ack),
		.b_lsb(b_lsb),
		.a_sel(a_sel),
		.b_sel(b_sel),
		.prod_sel(prod_sel),
		.add_sel(add_sel),
		.Done_Flag(Done_Flag)
	);

endmodule

testbench.v
`timescale 1ns/1ps
`include "multiplicador.v"

module tester(clk, reset, a, b, ack, Done_Flag, producto, valid_data);

	output [31:0] a,b;
	output clk, reset, valid_data, ack;
	input [63:0] producto;
	input Done_Flag;

	reg clk, reset, valid_data, ack;
	reg [31:0] a,b;
	wire [63:0] producto;

	initial begin

	//Se guarda lo que se obtiene en un archivo
	$dumpfile("kenny.vcd");
	$dumpvars;
	clk=0;
	a=34;
	b=76;
	valid_data=0;
	ack = 0;
	reset = 0;

	#50 reset = 1;
	#20 reset = 0;
	#20 valid_data = 1;	

	#400 $finish;
	end

	always @(*) 
	begin
		if (Done_Flag) begin
			ack = 1;	
		end
		else
		begin
			ack = 0;			
		end
	end

	initial begin #25 repeat(100) #5 clk=~clk; end

endmodule

module testbench;
		
	wire [63:0] producto;
	wire [31:0] a,b;
	
	tester test(clk, reset, a, b, ack, Done_Flag, producto, valid_data);
	multiplicador #(32) imul(producto, Done_Flag, a, b, clk, reset, valid_data, ack);

endmodule

primitivas.v
`timescale 1ns/1ps


`define SIZE_REG 32
`define SIZE_MUX 32
`define SIZE_ADDER 64


//------------------------------------------------------------------------------------------------------------------------
//------------------------------------------------------------------------------------------------------------------------
//Modulo de registro de N bits.
//------------------------------------------------------------------------------------------------------------------------
//------------------------------------------------------------------------------------------------------------------------
module regN(in,clk,clr,out,out_bar);
	
	parameter size = `SIZE_REG;
	
	// Se tienen las entradas:
	// - in: el dato de entrada, un vector de 32 bits.
	// - clk: reloj del registro.
	// - clr: reset del registro.
	// - out, out_bar: salidas del registro, son vectores de 32 bits.
	input [size-1:0] in;
	input clk,clr;
	output [size-1:0] out;
	output [size-1:0] out_bar;
	reg [size-1:0] out;
	reg [size-1:0] out_bar;
	reg [size-1:0]clear;
	
	// Se crea un bloque para definir la función que realiza un registro tipo PIPO (Parallel Input Parallel Output).
	always @(posedge clk) begin

		if (clr==0) begin 
		 
			out <= in;
			out_bar <= !in;
		
		end 
		
	end
	
	
	// Si ocurre un clr, la salida de los registros se vuelve 0 en q y 1 en q_bar.
	always @(posedge clr) begin
	
		
		
		clear = 0;
		
		if (clr==1) begin 
			out <= clear; 
			out_bar<= ~clear; 
		end
	
	end 

endmodule




//------------------------------------------------------------------------------------------------------------------------
//------------------------------------------------------------------------------------------------------------------------
//Modulo Multiplexor 2N a N
//------------------------------------------------------------------------------------------------------------------------
//------------------------------------------------------------------------------------------------------------------------

module mux2NaN(select, d1,d2, q);

	parameter size = `SIZE_MUX;

	input select;
	output [size-1:0]q;
	reg [size-1:0] q;
	input [size-1:0] d1,d2;

	//Secuencia de selección de datos
	always @(*) begin

		case(select)
		
			0: q <= d1;
			1: q <= d2;
			
		endcase

	end
	
endmodule






//------------------------------------------------------------------------------------------------------------------------
//------------------------------------------------------------------------------------------------------------------------
//Modulo sumador de N bits
//------------------------------------------------------------------------------------------------------------------------
//------------------------------------------------------------------------------------------------------------------------

module adderN(in1,in2,out);

	parameter size = `SIZE_ADDER;

	output [size-1:0]out;
	reg [size-1:0] out;
	input [size-1:0] in1,in2;

	//Secuencia de selección de datos
	always @(*) begin

	  out = in1+in2;

	end
	
endmodule


//------------------------------------------------------------------------------------------------------------------------
//------------------------------------------------------------------------------------------------------------------------
//Modulo Divisor de frecuencias
//------------------------------------------------------------------------------------------------------------------------
//------------------------------------------------------------------------------------------------------------------------
module divisorFrecuencia(clkin,seleccion,enable,clka,clkout);
	
	input clkin;
	input [1:0] seleccion;
	input enable;

	output clkout,clka;
	reg clkout,clka;

	wire clkin;
	reg clkin2;
	reg clkin4;
	reg clkin8;
	reg clkin16;

	initial 
	begin
	clkout = 1'b0;
	clka = 0;
	clkin2 = 0;
	clkin4 = 0;
	clkin8 = 0;
	clkin16 = 0;
	end

	
	always @ (posedge clkin) 
	begin 
		clkin2 <= !clkin2; 
	end

	always @ (posedge clkin2) 
	begin 
		clkin4 <= !clkin4; 
	end

	always @ (posedge clkin4) 
	begin 
		clkin8 <= !clkin8; 
	end

	always @ (posedge clkin8) 
	begin 
		clkin16 <= !clkin16; 
	end

	always @(enable or clkin) begin  
	  if(!enable)
	  
	    clka = clkin;
	  
	    if(seleccion == 0)
	      
	      clkout <= clkin2;

	    if(seleccion == 1)
	    
	      clkout <= clkin4;
	      
	    if(seleccion == 2)
	    
	      clkout <= clkin8;
	    
	    if(seleccion == 3)
	    
	      clkout <= clkin16;
	  else
	      clkout = 1'b0;
	end

	
endmodule 


//------------------------------------------------------------------------------------------------------------------------
//------------------------------------------------------------------------------------------------------------------------
//Modulo Reloj
//------------------------------------------------------------------------------------------------------------------------
//------------------------------------------------------------------------------------------------------------------------
module reloj(enable,clkout);

	input enable;

	output clkout;
	reg clkout;
	
	reg clk;
	
	initial clk = 0;
	
	always #3.2 clk = ~clk;
	
	always @(*)
	begin 
		if(enable)
	
		clkout = clk;
		
		else 
		
		clkout = 1'b0;
	end
	
endmodule

kenny.vcd
$date
	Sat Apr 25 23:10:18 2015
$end
$version
	Icarus Verilog
$end
$timescale
	1ps
$end
$scope module divisorFrecuencia $end
$var wire 1 ! clkin $end
$var wire 1 " enable $end
$var wire 2 # seleccion [1:0] $end
$var reg 1 $ clka $end
$var reg 1 % clkin16 $end
$var reg 1 & clkin2 $end
$var reg 1 ' clkin4 $end
$var reg 1 ( clkin8 $end
$var reg 1 ) clkout $end
$upscope $end
$scope module reloj $end
$var wire 1 * enable $end
$var reg 1 + clk $end
$var reg 1 , clkout $end
$upscope $end
$scope module testbench $end
$var wire 1 - Done_Flag $end
$var wire 32 . a [31:0] $end
$var wire 1 / ack $end
$var wire 32 0 b [31:0] $end
$var wire 1 1 clk $end
$var wire 64 2 producto [63:0] $end
$var wire 1 3 reset $end
$var wire 1 4 valid_data $end
$scope module test $end
$var wire 1 - Done_Flag $end
$var wire 64 5 producto [63:0] $end
$var reg 32 6 a [31:0] $end
$var reg 1 7 ack $end
$var reg 32 8 b [31:0] $end
$var reg 1 9 clk $end
$var reg 1 : reset $end
$var reg 1 ; valid_data $end
$upscope $end
$scope module imul $end
$var wire 1 - Done_Flag $end
$var wire 32 < a [31:0] $end
$var wire 1 = a_sel $end
$var wire 1 / ack $end
$var wire 1 > add_sel $end
$var wire 32 ? b [31:0] $end
$var wire 1 @ b_lsb $end
$var wire 1 A b_sel $end
$var wire 1 1 clk $end
$var wire 64 B prod [63:0] $end
$var wire 1 C prod_sel $end
$var wire 1 3 reset $end
$var wire 1 4 valid_data $end
$scope module data $end
$var wire 32 D a [31:0] $end
$var wire 32 E aShift [31:0] $end
$var wire 1 = a_sel $end
$var wire 64 F addResult [63:0] $end
$var wire 1 > add_sel $end
$var wire 32 G b [31:0] $end
$var wire 32 H bShift [31:0] $end
$var wire 1 @ b_lsb $end
$var wire 1 A b_sel $end
$var wire 1 1 clk $end
$var wire 64 I outAddSelMux [63:0] $end
$var wire 32 J outMuxA [31:0] $end
$var wire 32 K outMuxB [31:0] $end
$var wire 64 L outMuxProd [63:0] $end
$var wire 32 M outRegA [31:0] $end
$var wire 32 N outRegA_bar [31:0] $end
$var wire 32 O outRegB [31:0] $end
$var wire 32 P outRegB_bar [31:0] $end
$var wire 64 Q outRegProd [63:0] $end
$var wire 64 R outRegProd_bar [63:0] $end
$var wire 64 S prod [63:0] $end
$var wire 1 C prod_sel $end
$var wire 1 3 reset $end
$scope module muxA $end
$var wire 32 T d1 [31:0] $end
$var wire 32 U d2 [31:0] $end
$var wire 1 = select $end
$var reg 32 V q [31:0] $end
$upscope $end
$scope module muxB $end
$var wire 32 W d1 [31:0] $end
$var wire 32 X d2 [31:0] $end
$var wire 1 A select $end
$var reg 32 Y q [31:0] $end
$upscope $end
$scope module muxProd $end
$var wire 64 Z d1 [63:0] $end
$var wire 64 [ d2 [63:0] $end
$var wire 1 C select $end
$var reg 64 \ q [63:0] $end
$upscope $end
$scope module regA $end
$var wire 1 1 clk $end
$var wire 1 3 clr $end
$var wire 32 ] in [31:0] $end
$var reg 32 ^ clear [31:0] $end
$var reg 32 _ out [31:0] $end
$var reg 32 ` out_bar [31:0] $end
$upscope $end
$scope module regB $end
$var wire 1 1 clk $end
$var wire 1 3 clr $end
$var wire 32 a in [31:0] $end
$var reg 32 b clear [31:0] $end
$var reg 32 c out [31:0] $end
$var reg 32 d out_bar [31:0] $end
$upscope $end
$scope module regProd $end
$var wire 1 1 clk $end
$var wire 1 3 clr $end
$var wire 64 e in [63:0] $end
$var reg 64 f clear [63:0] $end
$var reg 64 g out [63:0] $end
$var reg 64 h out_bar [63:0] $end
$upscope $end
$scope module sumador64 $end
$var wire 64 i in1 [63:0] $end
$var wire 64 j in2 [63:0] $end
$var reg 64 k out [63:0] $end
$upscope $end
$scope module muxAddSel $end
$var wire 64 l d1 [63:0] $end
$var wire 64 m d2 [63:0] $end
$var wire 1 > select $end
$var reg 64 n q [63:0] $end
$upscope $end
$upscope $end
$scope module control $end
$var wire 1 1 Clock $end
$var wire 1 3 Reset $end
$var wire 1 / ack $end
$var wire 1 @ b_lsb $end
$var wire 1 4 valid_data $end
$var reg 2 o CurrentState [1:0] $end
$var reg 1 p Done_Flag $end
$var reg 2 q NextState [1:0] $end
$var reg 1 r a $end
$var reg 1 s a_sel $end
$var reg 1 t add_sel $end
$var reg 1 u b $end
$var reg 1 v b_sel $end
$var reg 1 w c $end
$var integer 32 x cont [31:0] $end
$var reg 1 y prod_sel $end
$upscope $end
$upscope $end
$upscope $end
$enddefinitions $end
#0
$dumpvars
xy
bx x
xw
xv
xu
xt
xs
xr
bx q
xp
bx o
bx n
bx m
bx l
bx k
bx j
b0xxxxxxxxxxxxxxxxxxxxxxxxxxxxxxxx i
bx h
bx g
bx f
bx e
bx d
bx c
bx b
bx a
bx `
bx _
bx ^
bx ]
bx \
bx [
b0 Z
bx Y
b0xxxxxxxxxxxxxxxxxxxxxxxxxxxxxxx X
b1001100 W
bx V
bx0 U
b100010 T
bx S
bx R
bx Q
bx P
bx O
bx N
bx M
bx L
bx K
bx J
bx I
b0xxxxxxxxxxxxxxxxxxxxxxxxxxxxxxx H
b1001100 G
bx F
bx0 E
b100010 D
xC
bx B
xA
x@
b1001100 ?
x>
x=
b100010 <
0;
0:
09
b1001100 8
07
b100010 6
bx 5
04
03
bx 2
01
b1001100 0
0/
b100010 .
x-
0,
0+
z*
0)
0(
0'
0&
0%
0$
bz #
z"
z!
$end
#3200
1+
#6400
0+
#9600
1+
#12800
0+
#16000
1+
#19200
0+
#22400
1+
#25600
0+
#28800
1+
#30000
b0x `
b0x N
b0x d
b0x P
b0x h
b0x R
b0 q
19
11
#32000
0+
#35000
09
01
#35200
1+
#38400
0+
#40000
b0 o
19
11
#41600
1+
#44800
0+
#45000
09
01
#48000
1+
#50000
b0 n
b0 I
b0 [
b1001100 Y
b1001100 K
b1001100 a
b100010 V
b100010 J
b100010 ]
b0 \
b0 L
b0 e
0t
0>
b0 E
b0 U
b0 H
b0 X
0@
b0 k
b0 F
b0 m
0p
0-
b0 x
0v
0A
0s
0=
0y
0C
b11111111111111111111111111111111 `
b11111111111111111111111111111111 N
b0 _
b0 i
b0 M
b11111111111111111111111111111111 d
b11111111111111111111111111111111 P
b0 c
b0 O
b1111111111111111111111111111111111111111111111111111111111111111 h
b1111111111111111111111111111111111111111111111111111111111111111 R
b0 g
b0 Q
b0 j
b0 l
b0 2
b0 5
b0 B
b0 S
0w
0u
0r
b0 ^
b0 b
b0 f
19
11
1:
13
#51200
0+
#54400
1+
#55000
09
01
#57600
0+
#60000
19
11
#60800
1+
#64000
0+
#65000
09
01
#67200
1+
#70000
b100010 k
b100010 F
b100010 m
b1000100 E
b1000100 U
b100110 H
b100110 X
b0 `
b0 N
b100010 _
b100010 i
b100010 M
b0 d
b0 P
b1001100 c
b1001100 O
b1 h
b1 R
19
11
0:
03
#70400
0+
#73600
1+
#75000
09
01
#76800
0+
#80000
1+
19
11
#83200
0+
#85000
09
01
#86400
1+
#89600
0+
#90000
b1 q
19
11
1;
14
#92800
1+
#95000
09
01
#96000
0+
#99200
1+
#100000
b1 o
19
11
#102400
0+
#105000
09
01
#105600
1+
#108800
0+
#110000
b100110 Y
b100110 K
b100110 a
b1000100 V
b1000100 J
b1000100 ]
b1 x
1v
1A
1s
1=
1y
1C
1u
19
11
#112000
1+
#115000
09
01
#115200
0+
#118400
1+
#120000
b10011 Y
b10011 K
b10011 a
b10001000 V
b10001000 J
b10001000 ]
b10011 H
b10011 X
b1000100 k
b1000100 F
b1000100 m
b10001000 E
b10001000 U
b10 x
b100110 c
b100110 O
b1000100 _
b1000100 i
b1000100 M
19
11
#121600
0+
#124800
1+
#125000
09
01
#128000
0+
#130000
b10001000 \
b10001000 L
b10001000 e
b10001000 n
b10001000 I
b10001000 [
b100010000 V
b100010000 J
b100010000 ]
b1001 Y
b1001 K
b1001 a
1t
1>
b10001000 k
b10001000 F
b10001000 m
b100010000 E
b100010000 U
b1001 H
b1001 X
1@
b10001000 _
b10001000 i
b10001000 M
b10011 c
b10011 O
b11 x
19
11
#131200
1+
#134400
0+
#135000
09
01
#137600
1+
#140000
b110011000 \
b110011000 L
b110011000 e
b100 Y
b100 K
b100 a
b1000100000 V
b1000100000 J
b1000100000 ]
b110011000 n
b110011000 I
b110011000 [
b100 H
b100 X
b110011000 k
b110011000 F
b110011000 m
b1000100000 E
b1000100000 U
b100 x
1r
b0 h
b0 R
b10001000 g
b10001000 Q
b10001000 j
b10001000 l
b10001000 2
b10001000 5
b10001000 B
b10001000 S
b1001 c
b1001 O
b100010000 _
b100010000 i
b100010000 M
19
11
#140800
0+
#144000
1+
#145000
09
01
#147200
0+
#150000
b10001000000 V
b10001000000 J
b10001000000 ]
b10 Y
b10 K
b10 a
b110011000 n
b110011000 I
b110011000 [
0t
0>
b10001000000 E
b10001000000 U
b10 H
b10 X
0@
b1110111000 k
b1110111000 F
b1110111000 m
b1000100000 _
b1000100000 i
b1000100000 M
b100 c
b100 O
b110011000 g
b110011000 Q
b110011000 j
b110011000 l
b110011000 2
b110011000 5
b110011000 B
b110011000 S
b101 x
19
11
#150400
1+
#153600
0+
#155000
09
01
#156800
1+
#160000
b1 Y
b1 K
b1 a
b100010000000 V
b100010000000 J
b100010000000 ]
b1 H
b1 X
b10111011000 k
b10111011000 F
b10111011000 m
b100010000000 E
b100010000000 U
b110 x
b10 c
b10 O
b10001000000 _
b10001000000 i
b10001000000 M
0+
19
11
#163200
1+
#165000
09
01
#166400
0+
#169600
1+
#170000
b101000011000 \
b101000011000 L
b101000011000 e
b101000011000 n
b101000011000 I
b101000011000 [
b1000100000000 V
b1000100000000 J
b1000100000000 ]
b0 Y
b0 K
b0 a
1t
1>
b101000011000 k
b101000011000 F
b101000011000 m
b1000100000000 E
b1000100000000 U
b0 H
b0 X
1@
b100010000000 _
b100010000000 i
b100010000000 M
b1 c
b1 O
b111 x
19
11
#172800
0+
#175000
09
01
#176000
1+
#179200
0+
#180000
b10001000000000 V
b10001000000000 J
b10001000000000 ]
b101000011000 n
b101000011000 I
b101000011000 [
0t
0>
0@
b1101100011000 k
b1101100011000 F
b1101100011000 m
b10001000000000 E
b10001000000000 U
b1000 x
b101000011000 g
b101000011000 Q
b101000011000 j
b101000011000 l
b101000011000 2
b101000011000 5
b101000011000 B
b101000011000 S
b1 d
b1 P
b0 c
b0 O
b1000100000000 _
b1000100000000 i
b1000100000000 M
19
11
#182400
1+
#185000
09
01
#185600
0+
#188800
1+
#190000
b100010000000000 V
b100010000000000 J
b100010000000000 ]
b10110000011000 k
b10110000011000 F
b10110000011000 m
b100010000000000 E
b100010000000000 U
b10001000000000 _
b10001000000000 i
b10001000000000 M
b1001 x
19
11
#192000
0+
#195000
09
01
#195200
1+
#198400
0+
#200000
b1000100000000000 V
b1000100000000000 J
b1000100000000000 ]
b100111000011000 k
b100111000011000 F
b100111000011000 m
b1000100000000000 E
b1000100000000000 U
b1010 x
b100010000000000 _
b100010000000000 i
b100010000000000 M
19
11
#201600
1+
#204800
0+
#205000
09
01
#208000
1+
#210000
b10001000000000000 V
b10001000000000000 J
b10001000000000000 ]
b1001001000011000 k
b1001001000011000 F
b1001001000011000 m
b10001000000000000 E
b10001000000000000 U
b1000100000000000 _
b1000100000000000 i
b1000100000000000 M
b1011 x
19
11
#211200
0+
#214400
1+
#215000
09
01
#217600
0+
#220000
b100010000000000000 V
b100010000000000000 J
b100010000000000000 ]
b10001101000011000 k
b10001101000011000 F
b10001101000011000 m
b100010000000000000 E
b100010000000000000 U
b1100 x
b10001000000000000 _
b10001000000000000 i
b10001000000000000 M
19
11
#220800
1+
#224000
0+
#225000
09
01
#227200
1+
#230000
b1000100000000000000 V
b1000100000000000000 J
b1000100000000000000 ]
b100010101000011000 k
b100010101000011000 F
b100010101000011000 m
b1000100000000000000 E
b1000100000000000000 U
b100010000000000000 _
b100010000000000000 i
b100010000000000000 M
b1101 x
19
11
#230400
0+
#233600
1+
#235000
09
01
#236800
0+
#240000
b10001000000000000000 V
b10001000000000000000 J
b10001000000000000000 ]
b1000100101000011000 k
b1000100101000011000 F
b1000100101000011000 m
b10001000000000000000 E
b10001000000000000000 U
b1110 x
b1000100000000000000 _
b1000100000000000000 i
b1000100000000000000 M
1+
19
11
#243200
0+
#245000
09
01
#246400
1+
#249600
0+
#250000
b100010000000000000000 V
b100010000000000000000 J
b100010000000000000000 ]
b10001000101000011000 k
b10001000101000011000 F
b10001000101000011000 m
b100010000000000000000 E
b100010000000000000000 U
b10001000000000000000 _
b10001000000000000000 i
b10001000000000000000 M
b1111 x
19
11
#252800
1+
#255000
09
01
#256000
0+
#259200
1+
#260000
b1000100000000000000000 V
b1000100000000000000000 J
b1000100000000000000000 ]
b100010000101000011000 k
b100010000101000011000 F
b100010000101000011000 m
b1000100000000000000000 E
b1000100000000000000000 U
b10000 x
b100010000000000000000 _
b100010000000000000000 i
b100010000000000000000 M
19
11
#262400
0+
#265000
09
01
#265600
1+
#268800
0+
#270000
b10001000000000000000000 V
b10001000000000000000000 J
b10001000000000000000000 ]
b1000100000101000011000 k
b1000100000101000011000 F
b1000100000101000011000 m
b10001000000000000000000 E
b10001000000000000000000 U
b1000100000000000000000 _
b1000100000000000000000 i
b1000100000000000000000 M
b10001 x
19
11
#272000
1+
#275000
09
01
#275200
0+
#278400
1+
#280000
b100010000000000000000000 V
b100010000000000000000000 J
b100010000000000000000000 ]
b10001000000101000011000 k
b10001000000101000011000 F
b10001000000101000011000 m
b100010000000000000000000 E
b100010000000000000000000 U
b10010 x
b10001000000000000000000 _
b10001000000000000000000 i
b10001000000000000000000 M
19
11
#281600
0+
#284800
1+
#285000
09
01
#288000
0+
#290000
b1000100000000000000000000 V
b1000100000000000000000000 J
b1000100000000000000000000 ]
b100010000000101000011000 k
b100010000000101000011000 F
b100010000000101000011000 m
b1000100000000000000000000 E
b1000100000000000000000000 U
b100010000000000000000000 _
b100010000000000000000000 i
b100010000000000000000000 M
b10011 x
19
11
#291200
1+
#294400
0+
#295000
09
01
#297600
1+
#300000
b10001000000000000000000000 V
b10001000000000000000000000 J
b10001000000000000000000000 ]
b1000100000000101000011000 k
b1000100000000101000011000 F
b1000100000000101000011000 m
b10001000000000000000000000 E
b10001000000000000000000000 U
b10100 x
b1000100000000000000000000 _
b1000100000000000000000000 i
b1000100000000000000000000 M
19
11
#300800
0+
#304000
1+
#305000
09
01
#307200
0+
#310000
b100010000000000000000000000 V
b100010000000000000000000000 J
b100010000000000000000000000 ]
b10001000000000101000011000 k
b10001000000000101000011000 F
b10001000000000101000011000 m
b100010000000000000000000000 E
b100010000000000000000000000 U
b10001000000000000000000000 _
b10001000000000000000000000 i
b10001000000000000000000000 M
b10101 x
19
11
#310400
1+
#313600
0+
#315000
09
01
#316800
1+
#320000
b1000100000000000000000000000 V
b1000100000000000000000000000 J
b1000100000000000000000000000 ]
b100010000000000101000011000 k
b100010000000000101000011000 F
b100010000000000101000011000 m
b1000100000000000000000000000 E
b1000100000000000000000000000 U
b10110 x
b100010000000000000000000000 _
b100010000000000000000000000 i
b100010000000000000000000000 M
0+
19
11
#323200
1+
#325000
09
01
#326400
0+
#329600
1+
#330000
b10001000000000000000000000000 V
b10001000000000000000000000000 J
b10001000000000000000000000000 ]
b1000100000000000101000011000 k
b1000100000000000101000011000 F
b1000100000000000101000011000 m
b10001000000000000000000000000 E
b10001000000000000000000000000 U
b1000100000000000000000000000 _
b1000100000000000000000000000 i
b1000100000000000000000000000 M
b10111 x
19
11
#332800
0+
#335000
09
01
#336000
1+
#339200
0+
#340000
b100010000000000000000000000000 V
b100010000000000000000000000000 J
b100010000000000000000000000000 ]
b10001000000000000101000011000 k
b10001000000000000101000011000 F
b10001000000000000101000011000 m
b100010000000000000000000000000 E
b100010000000000000000000000000 U
b11000 x
b10001000000000000000000000000 _
b10001000000000000000000000000 i
b10001000000000000000000000000 M
19
11
#342400
1+
#345000
09
01
#345600
0+
#348800
1+
#350000
b1000100000000000000000000000000 V
b1000100000000000000000000000000 J
b1000100000000000000000000000000 ]
b100010000000000000101000011000 k
b100010000000000000101000011000 F
b100010000000000000101000011000 m
b1000100000000000000000000000000 E
b1000100000000000000000000000000 U
b100010000000000000000000000000 _
b100010000000000000000000000000 i
b100010000000000000000000000000 M
b11001 x
19
11
#352000
0+
#355000
09
01
#355200
1+
#358400
0+
#360000
b10001000000000000000000000000000 V
b10001000000000000000000000000000 J
b10001000000000000000000000000000 ]
b1000100000000000000101000011000 k
b1000100000000000000101000011000 F
b1000100000000000000101000011000 m
b10001000000000000000000000000000 E
b10001000000000000000000000000000 U
b11010 x
b1000100000000000000000000000000 _
b1000100000000000000000000000000 i
b1000100000000000000000000000000 M
19
11
#361600
1+
#364800
0+
#365000
09
01
#368000
1+
#370000
b10000000000000000000000000000 V
b10000000000000000000000000000 J
b10000000000000000000000000000 ]
b10001000000000000000101000011000 k
b10001000000000000000101000011000 F
b10001000000000000000101000011000 m
b10000000000000000000000000000 E
b10000000000000000000000000000 U
b10001000000000000000000000000000 _
b10001000000000000000000000000000 i
b10001000000000000000000000000000 M
b11011 x
19
11
#371200
0+
#374400
1+
#375000
09
01
#377600
0+
#380000
b100000000000000000000000000000 V
b100000000000000000000000000000 J
b100000000000000000000000000000 ]
b10000000000000000101000011000 k
b10000000000000000101000011000 F
b10000000000000000101000011000 m
b100000000000000000000000000000 E
b100000000000000000000000000000 U
b11100 x
b10000000000000000000000000000 _
b10000000000000000000000000000 i
b10000000000000000000000000000 M
19
11
#380800
1+
#384000
0+
#385000
09
01
#387200
1+
#390000
b1000000000000000000000000000000 V
b1000000000000000000000000000000 J
b1000000000000000000000000000000 ]
b100000000000000000101000011000 k
b100000000000000000101000011000 F
b100000000000000000101000011000 m
b1000000000000000000000000000000 E
b1000000000000000000000000000000 U
b100000000000000000000000000000 _
b100000000000000000000000000000 i
b100000000000000000000000000000 M
b11101 x
19
11
#390400
0+
#393600
1+
#395000
09
01
#396800
0+
